{
    "Favourite Food": "Fish\r", 
    "Skin Type": "Smooth\r", 
    "Type": "Mammal\r", 
    "Kingdom": "Animalia\r", 
    "Scientific Name": "Tursiops Truncatus\r", 
    "img": "http://a-z-animals.com/media/animals/images/470x370/bottle_nosed_dolphin4.jpg", 
    "Diet": "Omnivore\r", 
    "Top Speed": "35km/h (21mph)\r", 
    "Distinctive Features": "Large dorsal fins and communicate using whistling", 
    "Average Litter Size": "1\r", 
    "Size (L)": "2.5m - 4m (8ft - 13ft)\r", 
    "Class": "Mammalia\r", 
    "Main Prey": "Fish, Shrimp, Squid\r", 
    "Lifestyle": "Pod\r", 
    "Colour": "Light grey, Dark grey\r", 
    "Life Span": "20 - 35 years\r", 
    "Predators": "Human, Sharks, Killer Whale\r", 
    "Genus": "Tursiops\r", 
    "Order": "Cetacea\r", 
    "Family": "Delphinidae\r", 
    "Habitat": "Warm harbours and bays\r", 
    "Conservation Status": "Least Concern\r", 
    "Weight": "200kg - 300kg (440lbs - 660lbs)\r", 
    "Phylum": "Chordata\r"
}