{
    "Favourite Food": "Insects", 
    "Skin Type": "Scales", 
    "Type": "Reptile", 
    "Kingdom": "Animalia", 
    "Scientific Name": "Gekkonidae", 
    "img": "http://a-z-animals.com/media/animals/images/470x370/gecko8.jpg", 
    "Diet": "Carnivore", 
    "Top Speed": "48km/h (30mph)", 
    "Average Litter Size": "2", 
    "Class": "Reptilia", 
    "Main Prey": "Insects, Worms, Small Birds", 
    "Lifestyle": "Solitary", 
    "Family": "Gekkonidae", 
    "Colour": "Tan, Black, Brown, White, Green, Blue, Orange, Yellow", 
    "Life Span": "2-9 years", 
    "Predators": "Snake, Birds, Spiders", 
    "Special Features": "Elongated body and able to walk up vertical surfaces", 
    "Genus": "Gekkoninae", 
    "Order": "Squamata", 
    "Weight": "18g (0.5oz)", 
    "Habitat": "Rocky deserts and mountainous regions", 
    "Conservation Status": "Threatened", 
    "Phylum": "Chordata", 
    "Size": "0.1-40cm (0.04-15.7in)"
}