{
    "Favourite Food": "Insects", 
    "Skin Type": "Feathers", 
    "Type": "Bird", 
    "Kingdom": "Animalia", 
    "Scientific Name": "Tetraoninae", 
    "img": "http://a-z-animals.com/media/animals/images/470x370/grouse3.jpg", 
    "Diet": "Omnivore", 
    "Top Speed": "10km/h (6mph)", 
    "Distinctive Features": "Long tail feathers and feathered legs and toes", 
    "Size (L)": "31cm - 95cm (12in - 37in)", 
    "Class": "Aves", 
    "Main Prey": "Insects, Nuts, Seeds, Berries", 
    "Lifestyle": "Flock", 
    "Average Clutch Size": "8", 
    "Colour": "Black, White, Brown, Yellow, Green, Blue, Red", 
    "Life Span": "1 - 10 years", 
    "Predators": "Fox, Lynx, Birds Of Prey", 
    "Genus": "Tetraoninae", 
    "Order": "Galliformes", 
    "Family": "Phasianidae", 
    "Habitat": "Forest, shrubland and grassy plains", 
    "Conservation Status": "Least Concern", 
    "Weight": "0.3kg - 6.5kg (0.6lbs - 14lbs)", 
    "Phylum": "Chordata", 
    "Wing Span": "45cm - 101cm (22in - 40in)"
}