{
    "Favourite Food": "Insects", 
    "Skin Type": "Feathers", 
    "Type": "Bird", 
    "Kingdom": "Animalia", 
    "Scientific Name": "Gallinula", 
    "img": "http://a-z-animals.com/media/animals/images/470x370/moorhen6.jpg", 
    "Diet": "Omnivore", 
    "Top Speed": "35km/h (22mph)", 
    "Distinctive Features": "Small rounded head and pointed beak", 
    "Size (L)": "25cm - 38cm (10in - 15in)", 
    "Class": "Aves", 
    "Main Prey": "Insects, Rodents, Berries", 
    "Lifestyle": "Flock", 
    "Average Clutch Size": "7", 
    "Colour": "Black, White, Brown", 
    "Life Span": "1 - 3 years", 
    "Predators": "Foxes, Dogs, Raccoons", 
    "Genus": "Gallinula", 
    "Order": "Gruiformes", 
    "Family": "Rallidae", 
    "Habitat": "Marshes, wetlands and ponds", 
    "Conservation Status": "Least Concern", 
    "Weight": "70g - 400g (2.5oz - 14oz)", 
    "Phylum": "Chordata", 
    "Wing Span": "50cm - 80cm (20in - 31in)"
}